pytket/extensions/pyquil/__init__.py
pytket/extensions/pyquil/_metadata.py
pytket/extensions/pyquil/py.typed
pytket/extensions/pyquil/pyquil_convert.py
pytket/extensions/pyquil/backends/__init__.py
pytket/extensions/pyquil/backends/forest.py
pytket_pyquil-0.40.0.dist-info/licenses/LICENSE
pytket_pyquil-0.40.0.dist-info/METADATA
pytket_pyquil-0.40.0.dist-info/WHEEL
pytket_pyquil-0.40.0.dist-info/top_level.txt
pytket_pyquil-0.40.0.dist-info/RECORD
