Metadata-Version: 2.4
Name: pytket-pyquil
Version: 0.40.0
Summary: Extension for pytket, providing translation to and from the pyQuil framework
Author: TKET development team
Author-email: tket-support@quantinuum.com
License: Apache 2
Project-URL: Documentation, https://tket.quantinuum.com/extensions/pytket-pyquil/index.html
Project-URL: Source, https://github.com/CQCL/pytket-pyquil
Project-URL: Tracker, https://github.com/CQCL/pytket-pyquil/issues
Classifier: Environment :: Console
Classifier: Programming Language :: Python :: 3.10
Classifier: Programming Language :: Python :: 3.11
Classifier: Programming Language :: Python :: 3.12
Classifier: License :: OSI Approved :: Apache Software License
Classifier: Operating System :: MacOS :: MacOS X
Classifier: Operating System :: POSIX :: Linux
Classifier: Operating System :: Microsoft :: Windows
Classifier: Intended Audience :: Developers
Classifier: Intended Audience :: Science/Research
Classifier: Topic :: Scientific/Engineering
Requires-Python: >=3.10
License-File: LICENSE
Requires-Dist: pytket>=2.0.1
Requires-Dist: pyquil>=4.13.0
Requires-Dist: typing-extensions>=4.12.2
Requires-Dist: qcs-sdk-python==0.20.1
Dynamic: author
Dynamic: author-email
Dynamic: classifier
Dynamic: description
Dynamic: description-content-type
Dynamic: license
Dynamic: license-file
Dynamic: project-url
Dynamic: requires-dist
Dynamic: requires-python
Dynamic: summary
